pico_dspy/__init__.py
pico_dspy/adapters/__init__.py
pico_dspy/adapters/json_adapter.py
pico_dspy/adapters/utils.py
pico_dspy/adapters/types/__init__.py
pico_dspy/adapters/types/history.py
pico_dspy/clients/__init__.py
pico_dspy/clients/lm.py
pico_dspy/predict/__init__.py
pico_dspy/predict/predict.py
pico_dspy/primitives/__init__.py
pico_dspy/primitives/prediction.py
pico_dspy/signatures/__init__.py
pico_dspy/signatures/field.py
pico_dspy/signatures/signature.py
pico_dspy/signatures/utils.py
pico_dspy/utils/__init__.py
pico_dspy/utils/exceptions.py
pico_dspy-0.2.dist-info/licenses/LICENSE
pico_dspy-0.2.dist-info/METADATA
pico_dspy-0.2.dist-info/WHEEL
pico_dspy-0.2.dist-info/top_level.txt
pico_dspy-0.2.dist-info/RECORD
