Metadata-Version: 2.4
Name: pico-dspy
Version: 0.2
Author-email: Marcin Bachry <hegel666@gmail.com>
Requires-Python: >=3.12
License-File: LICENSE
Requires-Dist: json-repair>=0.54.2
Requires-Dist: pydantic>=2.0
Requires-Dist: regex>=2023.10.3
Requires-Dist: wrapt
Dynamic: license-file
